pycuda_plus/__init__.py
pycuda_plus/core/__init__.py
pycuda_plus/core/async.py
pycuda_plus/core/context.py
pycuda_plus/core/error.py
pycuda_plus/core/grid_block.py
pycuda_plus/core/kernel.py
pycuda_plus/core/memory.py
pycuda_plus/core/profiler.py
pycuda_plus/plugins/__init__.py
pycuda_plus/plugins/example_plugin.py
pycuda_plus/plugins/plugin_manager.py
pycuda_plus/tests/__init__.py
pycuda_plus/tests/test_context.py
pycuda_plus/tests/test_integration.py
pycuda_plus/tests/test_kernel.py
pycuda_plus/tests/test_memory.py
pycuda_plus/tests/test_utils.py
pycuda_plus/utils/__init__.py
pycuda_plus/utils/math_ops.py
pycuda_plus/utils/monitor.py
pycuda_plus/utils/numpy_support.py
pycuda_plus/utils/prebuilt_kernels.py
pycuda_plus/utils/tensor_support.py
pycuda_plus/utils/visualization.py
pycuda_plus-0.3.1.dist-info/METADATA
pycuda_plus-0.3.1.dist-info/WHEEL
pycuda_plus-0.3.1.dist-info/top_level.txt
pycuda_plus-0.3.1.dist-info/RECORD
