Metadata-Version: 2.1
Name: pycuda_plus
Version: 0.3.1
Summary: User-friendly library to enhance PyCUDA functionality
Home-page: https://github.com/takuphilchan/pycuda_plus
Author: Phillip Chananda
Author-email: takuphilchan@gmail.com
Project-URL: Bug Tracker, https://github.com/takuphilchan/pycuda_plus/issues
Project-URL: Documentation, https://github.com/takuphilchan/pycuda_plus#readme
Project-URL: Source Code, https://github.com/takuphilchan/pycuda_plus
Classifier: Development Status :: 4 - Beta
Classifier: Intended Audience :: Developers
Classifier: Topic :: Software Development :: Libraries :: Python Modules
Classifier: Programming Language :: Python :: 3
Classifier: License :: OSI Approved :: MIT License
Classifier: Operating System :: OS Independent
Requires-Python: >=3.7
Requires-Dist: pycuda
Requires-Dist: numpy
Requires-Dist: six
Requires-Dist: matplotlib
Requires-Dist: seaborn
Requires-Dist: pandas
Requires-Dist: dash
Requires-Dist: plotly
Requires-Dist: cupy-cuda12x
